amqp_rpc_server/__init__.py
amqp_rpc_server/basic_consumer.py
amqp_rpc_server/exceptions.py
amqp_rpc_server-1.2.4.dist-info/LICENSE
amqp_rpc_server-1.2.4.dist-info/METADATA
amqp_rpc_server-1.2.4.dist-info/WHEEL
amqp_rpc_server-1.2.4.dist-info/top_level.txt
amqp_rpc_server-1.2.4.dist-info/RECORD
