Metadata-Version: 2.1
Name: amqp-rpc-server
Version: 1.2.4
Summary: A RPC server based on AMQPv0-9-1-enabled message broker
Home-page: https://github.com/j-suchard/amqp-rpc-client
Author: Jan Eike Suchard
Author-email: jan-eike.suchard@magenta.de
Classifier: Programming Language :: Python :: 3
Classifier: License :: OSI Approved :: BSD License
Classifier: Topic :: Software Development :: Libraries
Classifier: Operating System :: OS Independent
Requires-Python: >=3.6
License-File: LICENSE
Requires-Dist: pika (~=1.2.0)
